accoladecli-1.1.data/scripts/accolade
accoladecli-1.1.data/scripts/sa.py
accoladecli-1.1.dist-info/METADATA
accoladecli-1.1.dist-info/RECORD
accoladecli-1.1.dist-info/WHEEL
accoladecli-1.1.dist-info/top_level.txt
cliparser/__init__.py
cliparser/argparser.py
cliparser/os.py
cliparser/play.py
cliparser/sa.py
cliparser/security.py
cliparser/tradeoff.py
parser/__init__.py
parser/argparser.py
parser/os.py
parser/play.py
parser/sa.py
